adt7410.py
circuitpython_adt7410-0.1.0.dist-info/LICENSE
circuitpython_adt7410-0.1.0.dist-info/METADATA
circuitpython_adt7410-0.1.0.dist-info/WHEEL
circuitpython_adt7410-0.1.0.dist-info/top_level.txt
circuitpython_adt7410-0.1.0.dist-info/RECORD
