Metadata-Version: 2.1
Name: circuitpython-adt7410
Version: 0.1.0
Summary: CircuitPython Driver for the Analog Devices ADT7410 Temperature Sensor
Author-email: JDM <xxx@mailmeto.mozmail.com>
License: MIT
Project-URL: Homepage, https://github.com/jposada202020/CircuitPython_ADT7410
Keywords: sensor,blinka,circuitpython,adt7410,temperature
Classifier: Intended Audience :: Developers
Classifier: Topic :: Software Development :: Libraries
Classifier: Topic :: Software Development :: Embedded Systems
Classifier: Topic :: System :: Hardware
Classifier: License :: OSI Approved :: MIT License
Classifier: Programming Language :: Python :: 3
License-File: LICENSE
Requires-Dist: Adafruit-Blinka
Requires-Dist: adafruit-circuitpython-busdevice
Requires-Dist: adafruit-circuitpython-register
Provides-Extra: optional
